MANIFEST.in
README.md
VERSION
setup.py
django_osgeo_importer_client.egg-info/PKG-INFO
django_osgeo_importer_client.egg-info/SOURCES.txt
django_osgeo_importer_client.egg-info/dependency_links.txt
django_osgeo_importer_client.egg-info/not-zip-safe
django_osgeo_importer_client.egg-info/top_level.txt
osgeo_importer_client/__init__.py
osgeo_importer_client/static/osgeo_importer_client/js/osgeo_importer_client.min.js
osgeo_importer_client/templates/osgeo_importer_client/bulk_import.html