Metadata-Version: 1.0
Name: django-osgeo-importer-client
Version: 0.0.6
Summary: Use GeoNode OSGeo Importer in your django projects
Home-page: https://github.com/GeoNode/osgeo-importer-client
Author: Mila Frerichs
Author-email: mila.frerichs@gmail.com
License: LGPL, see LICENSE file.
Platform: UNKNOWN
